CHANGES.rst
COPYING.LGPLv3
MANIFEST.in
README.rst
setup.py
django_inplaceedit.egg-info/PKG-INFO
django_inplaceedit.egg-info/SOURCES.txt
django_inplaceedit.egg-info/dependency_links.txt
django_inplaceedit.egg-info/not-zip-safe
django_inplaceedit.egg-info/top_level.txt
inplaceeditform/__init__.py
inplaceeditform/adaptors.py
inplaceeditform/commons.py
inplaceeditform/fields.py
inplaceeditform/perms.py
inplaceeditform/settings.py
inplaceeditform/tag_utils.py
inplaceeditform/urls.py
inplaceeditform/views.py
inplaceeditform/locale/ca/LC_MESSAGES/django.mo
inplaceeditform/locale/ca/LC_MESSAGES/django.po
inplaceeditform/locale/cs/LC_MESSAGES/django.mo
inplaceeditform/locale/cs/LC_MESSAGES/django.po
inplaceeditform/locale/en/LC_MESSAGES/django.mo
inplaceeditform/locale/en/LC_MESSAGES/django.po
inplaceeditform/locale/es/LC_MESSAGES/django.mo
inplaceeditform/locale/es/LC_MESSAGES/django.po
inplaceeditform/locale/pl/LC_MESSAGES/django.mo
inplaceeditform/locale/pl/LC_MESSAGES/django.po
inplaceeditform/locale/pt_BR/LC_MESSAGES/django.mo
inplaceeditform/locale/pt_BR/LC_MESSAGES/django.po
inplaceeditform/static/css/inplaceedit_structure.css
inplaceeditform/static/css/inplaceedit_style.css
inplaceeditform/static/css/inplaceedit_toolbar_structure.css
inplaceeditform/static/css/inplaceedit_toolbar_style.css
inplaceeditform/static/img/apply.gif
inplaceeditform/static/img/cancel.gif
inplaceeditform/static/img/false.gif
inplaceeditform/static/img/load.png
inplaceeditform/static/img/true.gif
inplaceeditform/static/js/DateTimeShortcutsInitial.js
inplaceeditform/static/js/jquery.form.js
inplaceeditform/static/js/jquery.init.js
inplaceeditform/static/js/jquery.inplaceeditform.hooks.js
inplaceeditform/static/js/jquery.inplaceeditform.js
inplaceeditform/static/js/jquery.json.js
inplaceeditform/templates/inplaceeditform/inc.csrf_token.html
inplaceeditform/templates/inplaceeditform/inc.extra_options.html
inplaceeditform/templates/inplaceeditform/inc.inplace_toolbar.html
inplaceeditform/templates/inplaceeditform/inplace_css.html
inplaceeditform/templates/inplaceeditform/inplace_edit.html
inplaceeditform/templates/inplaceeditform/inplace_js.html
