Metadata-Version: 1.1
Name: django-inplaceedit
Version: 1.4.0
Summary: Django application that allows you to inline edition of some data from the database
Home-page: https://github.com/django-inplaceedit/django-inplaceedit
Author: Pablo Martin
Author-email: goinnn@gmail.com
License: LGPL 3
Keywords: django,inplace,inline edit,inline form,inline,inplace edit,inplace form,ajax
Platform: UNKNOWN
Classifier: Development Status :: 5 - Production/Stable
Classifier: Framework :: Django
Classifier: License :: OSI Approved :: GNU Library or Lesser General Public License (LGPL)
Classifier: Programming Language :: Python :: 2
Classifier: Programming Language :: Python :: 3
